scospus/__init__.py
scospus/airbuscsv.py
scospus/crc16.py
scospus/dds.py
scospus/enums.py
scospus/guess.py
scospus/internal.py
scospus/pus.py
scospus/tc.py
scospus/tm.py
scospus/version.py
scospus-0.2.0.dist-info/LICENSE
scospus-0.2.0.dist-info/METADATA
scospus-0.2.0.dist-info/WHEEL
scospus-0.2.0.dist-info/top_level.txt
scospus-0.2.0.dist-info/RECORD
